bettershot/__init__.py
bettershot-0.1.92.dist-info/METADATA
bettershot-0.1.92.dist-info/WHEEL
bettershot-0.1.92.dist-info/RECORD
